contextlib3/__init__.py
contextlib3-3.10.0.dist-info/LICENSE
contextlib3-3.10.0.dist-info/WHEEL
contextlib3-3.10.0.dist-info/METADATA
contextlib3-3.10.0.dist-info/RECORD
